creative_namer.py
creative_namer-1.1.1.dist-info/METADATA
creative_namer-1.1.1.dist-info/WHEEL
creative_namer-1.1.1.dist-info/entry_points.txt
creative_namer-1.1.1.dist-info/top_level.txt
creative_namer-1.1.1.dist-info/RECORD
