Metadata-Version: 2.1
Name: creative-namer
Version: 1.1.1
Summary: UNKNOWN
Home-page: UNKNOWN
License: UNKNOWN
Platform: UNKNOWN
Requires-Dist: openai-chat-thread
